alfred_docker_compose/__init__.py
alfred_docker_compose/aflred_dc.py
alfred_docker_compose/main.py
alfred_docker_compose/run_parse_log.py
alfred_docker_compose/runbot_docker.py
alfred_docker_compose-1.0.0.dist-info/METADATA
alfred_docker_compose-1.0.0.dist-info/WHEEL
alfred_docker_compose-1.0.0.dist-info/entry_points.txt
alfred_docker_compose-1.0.0.dist-info/top_level.txt
alfred_docker_compose-1.0.0.dist-info/RECORD
