Metadata-Version: 2.1
Name: alfred-docker-compose
Version: 1.0.0
Summary: Alfred
Author: Alexis Pasquier, Alexis Braine
Author-email: alexis.pasquier@ndp-systemees.fr, alexis.braine@ndp-systemes.fr
License: GPLv3
Platform: UNKNOWN
Requires-Dist: python-on-whales (==0.43.0)
Requires-Dist: ndp-utils (>=1.0.0)
Requires-Dist: addons-installer (==1.5.0)
